specsoloist/__init__.py
specsoloist/cli.py
specsoloist/compiler.py
specsoloist/config.py
specsoloist/core.py
specsoloist/manifest.py
specsoloist/parser.py
specsoloist/resolver.py
specsoloist/runner.py
specsoloist/server.py
specsoloist/ui.py
specsoloist/providers/__init__.py
specsoloist/providers/anthropic.py
specsoloist/providers/base.py
specsoloist/providers/gemini.py
specsoloist/templates/__init__.py
specsoloist/templates/global_context.md
specsoloist/templates/spec_template.md
specsoloist-0.2.0.dist-info/METADATA
specsoloist-0.2.0.dist-info/WHEEL
specsoloist-0.2.0.dist-info/entry_points.txt
specsoloist-0.2.0.dist-info/licenses/LICENSE
specsoloist-0.2.0.dist-info/RECORD
