Metadata-Version: 2.4
Name: specsoloist
Version: 0.2.0
Summary: Spec-as-Source Framework: AI-driven development where specifications are the source of truth.
Project-URL: Homepage, https://github.com/symbolfarm/specsoloist
Project-URL: Repository, https://github.com/symbolfarm/specsoloist
Project-URL: Issues, https://github.com/symbolfarm/specsoloist/issues
Author-email: Toby Lightheart <code@symbolfarm.com>
License-Expression: MIT
License-File: LICENSE
Keywords: ai,code-generation,llm,mcp,specifications
Classifier: Development Status :: 3 - Alpha
Classifier: Intended Audience :: Developers
Classifier: License :: OSI Approved :: MIT License
Classifier: Programming Language :: Python :: 3
Classifier: Programming Language :: Python :: 3.10
Classifier: Programming Language :: Python :: 3.11
Classifier: Programming Language :: Python :: 3.12
Classifier: Topic :: Software Development :: Code Generators
Requires-Python: >=3.10
Requires-Dist: mcp>=0.1.0
Requires-Dist: pyyaml>=6.0
Requires-Dist: rich>=13.0.0
Provides-Extra: dev
Requires-Dist: mkdocs-material>=9.0.0; extra == 'dev'
Requires-Dist: mkdocs>=1.5.0; extra == 'dev'
Requires-Dist: pytest>=7.0; extra == 'dev'
Requires-Dist: ruff>=0.1.0; extra == 'dev'
